botfights/__init__.py
botfights/wordle/README.md
botfights/wordle/__init__.py
botfights/wordle/bot.txt
botfights/wordle/human.txt
botfights/wordle/sample_bot.py
botfights/wordle/wordle.py
botfights-0.1.dist-info/LICENSE
botfights-0.1.dist-info/METADATA
botfights-0.1.dist-info/WHEEL
botfights-0.1.dist-info/entry_points.txt
botfights-0.1.dist-info/top_level.txt
botfights-0.1.dist-info/RECORD
