Metadata-Version: 2.1
Name: botfights
Version: 0.1
Summary: UNKNOWN
Home-page: UNKNOWN
License: UNKNOWN
Platform: UNKNOWN
License-File: LICENSE
Requires-Dist: fire
Requires-Dist: requests
